examples/__init__.py
mr_uplift/__init__.py
mr_uplift/calibrate_uplift.py
mr_uplift/erupt.py
mr_uplift/keras_model_functionality.py
mr_uplift/mr_uplift.py
mr_uplift/dataset/__init__.py
mr_uplift/dataset/data_simulation.py
tests/__init__.py
tests/test_calibrate.py
tests/test_mr_uplift.py
mr_uplift-0.0.14.dist-info/LICENSE
mr_uplift-0.0.14.dist-info/METADATA
mr_uplift-0.0.14.dist-info/NOTICE
mr_uplift-0.0.14.dist-info/WHEEL
mr_uplift-0.0.14.dist-info/top_level.txt
mr_uplift-0.0.14.dist-info/RECORD
